rsaitehu/ransac.py
rsaitehu_ransac-0.0.6.dist-info/METADATA
rsaitehu_ransac-0.0.6.dist-info/WHEEL
rsaitehu_ransac-0.0.6.dist-info/top_level.txt
rsaitehu_ransac-0.0.6.dist-info/RECORD
