Metadata-Version: 2.1
Name: rsaitehu-ransac
Version: 0.0.6
Summary: ransac utilities
Requires-Dist: numpy >=1.22.0
Requires-Dist: open3d >=0.16.0
Requires-Dist: rsaitehu-geometry >=0.0.1
Requires-Dist: rsaitehu-sampling >=0.0.1
